klayout_pex/__init__.py
klayout_pex/__main__.py
klayout_pex/common/__init__.py
klayout_pex/common/capacitance_matrix.py
klayout_pex/common/path_validation.py
klayout_pex/env.py
klayout_pex/extraction_engine.py
klayout_pex/fastcap/__init__.py
klayout_pex/fastcap/fastcap_runner.py
klayout_pex/fastercap/__init__.py
klayout_pex/fastercap/fastercap_input_builder.py
klayout_pex/fastercap/fastercap_model_generator.py
klayout_pex/fastercap/fastercap_runner.py
klayout_pex/klayout/__init__.py
klayout_pex/klayout/lvs_runner.py
klayout_pex/klayout/lvsdb_extractor.py
klayout_pex/klayout/netlist_csv.py
klayout_pex/klayout/netlist_expander.py
klayout_pex/klayout/netlist_printer.py
klayout_pex/klayout/netlist_reducer.py
klayout_pex/klayout/repair_rdb.py
klayout_pex/klayout/rex_core.py
klayout_pex/klayout/shapes_pb2_converter.py
klayout_pex/kpex_cli.py
klayout_pex/log/__init__.py
klayout_pex/log/logger.py
klayout_pex/magic/__init__.py
klayout_pex/magic/magic_ext_data_structures.py
klayout_pex/magic/magic_ext_file_parser.py
klayout_pex/magic/magic_log_analyzer.py
klayout_pex/magic/magic_runner.py
klayout_pex/netlist/__init__.py
klayout_pex/netlist/__main__.py
klayout_pex/netlist/netlist_cli.py
klayout_pex/netlistsvg/netlist_json.py
klayout_pex/netlistsvg/netlistsvg_runner.py
klayout_pex/pdk_config.py
klayout_pex/rcx25/__init__.py
klayout_pex/rcx25/c/__init__.py
klayout_pex/rcx25/c/geometry_restorer.py
klayout_pex/rcx25/c/overlap_extractor.py
klayout_pex/rcx25/c/polygon_utils.py
klayout_pex/rcx25/c/sidewall_and_fringe_extractor.py
klayout_pex/rcx25/extraction_reporter.py
klayout_pex/rcx25/extraction_results.py
klayout_pex/rcx25/extractor.py
klayout_pex/rcx25/netlist_expander.py
klayout_pex/rcx25/pex_mode.py
klayout_pex/rcx25/r/__init__.py
klayout_pex/rcx25/r/conductance.py
klayout_pex/rcx25/r/r_extractor.py
klayout_pex/rcx25/r/resistor_network.py
klayout_pex/rcx25/types.py
klayout_pex/tech_info.py
klayout_pex/util/__init__.py
klayout_pex/util/argparse_helpers.py
klayout_pex-0.3.7.dist-info/METADATA
klayout_pex-0.3.7.dist-info/WHEEL
klayout_pex-0.3.7.dist-info/entry_points.txt
klayout_pex-0.3.7.dist-info/licenses/LICENSE
klayout_pex-0.3.7.dist-info/RECORD
