Metadata-Version: 2.4
Name: klayout-pex
Version: 0.3.7
Summary: Parasitic Extraction Tool for KLayout
License: GPL-3.0-or-later
License-File: LICENSE
Keywords: electronic,pex,parasitic,extraction,vlsi,eda,ic,spice,klayout,analog,fsic,gds,FasterCap,magic
Author: Martin Köhler
Author-email: info@martinjankoehler.com
Requires-Python: >=3.12,<4.0
Classifier: Development Status :: 2 - Pre-Alpha
Classifier: Environment :: Console
Classifier: Intended Audience :: Manufacturing
Classifier: Intended Audience :: Science/Research
Classifier: License :: OSI Approved :: GNU General Public License v3 or later (GPLv3+)
Classifier: Operating System :: MacOS
Classifier: Operating System :: Microsoft :: Windows
Classifier: Operating System :: POSIX
Classifier: Programming Language :: C++
Classifier: Programming Language :: Python :: 3
Classifier: Programming Language :: Python :: 3.12
Classifier: Programming Language :: Python :: 3.13
Classifier: Programming Language :: Python :: 3.14
Classifier: Programming Language :: Python :: 3 :: Only
Classifier: Topic :: Scientific/Engineering
Classifier: Topic :: Scientific/Engineering :: Electronic Design Automation (EDA)
Requires-Dist: cairosvg (>=2.7.1)
Requires-Dist: klayout (>=0.30.3)
Requires-Dist: matplotlib (>=3.10.1)
Requires-Dist: protobuf (>=6.31.0)
Requires-Dist: rich (>=13.9.4)
Requires-Dist: rich-argparse (>=1.6.0)
Project-URL: Bug Tracker, https://github.com/iic-jku/klayout-pex/issues
Project-URL: Homepage, https://iic-jku.github.io/klayout-pex-website/
Project-URL: Repository, https://github.com/iic-jku/klayout-pex.git
